onecode/__init__.py
onecode/base/__init__.py
onecode/base/decorator.py
onecode/base/enums.py
onecode/base/logger.py
onecode/base/project.py
onecode/base/singleton.py
onecode/cli/__init__.py
onecode/cli/add.py
onecode/cli/build.py
onecode/cli/check.py
onecode/cli/create.py
onecode/cli/extract.py
onecode/cli/require.py
onecode/cli/skeleton/.gitignore
onecode/cli/skeleton/LICENSE
onecode/cli/skeleton/README.md
onecode/cli/skeleton/data/README.md
onecode/cli/skeleton/flows/README.md
onecode/cli/skeleton/main.py
onecode/cli/skeleton/requirements.txt
onecode/cli/start.py
onecode/cli/utils.py
onecode/cli/zip.py
onecode/elements/__init__.py
onecode/elements/input/__init__.py
onecode/elements/input/__init__.pyi
onecode/elements/input/checkbox.py
onecode/elements/input/csv_reader.py
onecode/elements/input/dropdown.py
onecode/elements/input/file_input.py
onecode/elements/input/number_input.py
onecode/elements/input/radio_button.py
onecode/elements/input/slider.py
onecode/elements/input/text_input.py
onecode/elements/input_element.py
onecode/elements/output/__init__.py
onecode/elements/output/__init__.pyi
onecode/elements/output/file_output.py
onecode/elements/output_element.py
onecode/utils/__init__.py
onecode/utils/import_input.py
onecode/utils/import_output.py
onecode/utils/module.py
onecode/utils/typing.py
onecode-1.1.0.dist-info/LICENSE
onecode-1.1.0.dist-info/METADATA
onecode-1.1.0.dist-info/WHEEL
onecode-1.1.0.dist-info/entry_points.txt
onecode-1.1.0.dist-info/RECORD
