Metadata-Version: 2.3
Name: onecode
Version: 1.1.0
Summary: Python skeleton and library for OneCode projects
License: MIT
Keywords: onecode,share,deploy,cloud
Author: DeepLime
Author-email: contact@deeplime.io
Requires-Python: >=3.8,<3.13
Classifier: Development Status :: 5 - Production/Stable
Classifier: Intended Audience :: Developers
Classifier: Intended Audience :: End Users/Desktop
Classifier: License :: OSI Approved :: MIT License
Classifier: Natural Language :: English
Classifier: Operating System :: Microsoft :: Windows
Classifier: Operating System :: Unix
Classifier: Programming Language :: Python
Classifier: Programming Language :: Python :: 3
Classifier: Programming Language :: Python :: 3.8
Classifier: Programming Language :: Python :: 3.9
Classifier: Programming Language :: Python :: 3.10
Classifier: Programming Language :: Python :: 3.11
Classifier: Programming Language :: Python :: 3.12
Classifier: Topic :: Scientific/Engineering
Classifier: Topic :: Software Development :: Code Generators
Provides-Extra: developer
Provides-Extra: docs
Requires-Dist: astunparse (>=1.6.3,<2)
Requires-Dist: datatest (>=0.11.1,<1) ; extra == "developer"
Requires-Dist: flufl.lock (>=7.1.1,<9)
Requires-Dist: griffe (>=0,<1) ; extra == "docs"
Requires-Dist: inquirerpy (>=0.3.3,<1)
Requires-Dist: mike (>=1.1,<1.2) ; extra == "docs"
Requires-Dist: mkdocs (>=1.5,<2.0) ; extra == "docs"
Requires-Dist: mkdocs-material (>=9.5,<10.0) ; extra == "docs"
Requires-Dist: mkdocstrings (>=0,<1) ; extra == "docs"
Requires-Dist: mkdocstrings-python (>=1,<2) ; extra == "docs"
Requires-Dist: onecode-pycg (>=0.0.7,<1)
Requires-Dist: pandas (>=1.4.0,<3)
Requires-Dist: pydantic (>=2,<3) ; extra == "developer"
Requires-Dist: pydash (>=5.1.0,<8)
Requires-Dist: pytest (>=7,<8) ; extra == "developer"
Requires-Dist: pytest-cov (>=2.10.1,<5) ; extra == "developer"
Requires-Dist: pytest-xdist (>=3.1.0,<4) ; extra == "developer"
Requires-Dist: python-slugify (>=6.1.2,<9)
Requires-Dist: requirements-parser (>=0.10.2,<1)
Requires-Dist: strenum (>=0.4.6,<1)
Requires-Dist: toml (>=0.10.2,<1) ; extra == "developer"
Requires-Dist: typeguard (>=3,<5)
Requires-Dist: yaspin (>=2.1.0,<4)
Project-URL: Documentation, https://deeplime-io.github.io/onecode
Project-URL: Homepage, https://github.com/deeplime-io/onecode
Project-URL: Repository, https://github.com/deeplime-io/onecode
